[
  {
    "id": "act_001",
    "title": "Escuchar un podcast juntos",
    "description": "Descubran historias fascinantes, ciencia, comedia o misterio mientras comparten el momento.",
    "tags": ["podcast", "audio", "indoor", "passive", "learning", "relaxing"],
    "min_duration_min": 20,
    "max_duration_min": 60,
    "intensity": 0,
    "cost": 0,
    "participants": 2,
    "required_assets": ["YouTube"],
    "suitability": {
      "mood": ["tired", "calm"],
      "time_of_day": ["evening", "night", "afternoon"]
    },
    "steps": [
      "Elijan un tema que les interese a ambos",
      "Pónganse cómodos (en el sillón, en la cama, etc.)",
      "Reproduzcan y escuchen juntos",
      "Comenten lo que les llamó la atención"
    ]
  },
  {
    "id": "act_002",
    "title": "Jugar videojuegos cooperativos",
    "description": "Elijan un juego que puedan jugar juntos, ya sea cooperativo o competitivo amigable.",
    "tags": ["gaming", "videogames", "indoor", "active", "fun", "playful"],
    "min_duration_min": 30,
    "max_duration_min": 120,
    "intensity": 1,
    "cost": 0,
    "participants": 2,
    "required_assets": ["Consola, teléfono o PC"],
    "suitability": {
      "mood": ["energetic", "fun"],
      "time_of_day": ["afternoon", "evening", "night"]
    },
    "steps": [
      "Elijan el juego (cooperativo preferentemente)",
      "Configuren controles y dificultad",
      "Jueguen sin presión, lo importante es pasarla bien",
      "Tomen pausas si es sesión larga"
    ]
  },
  {
    "id": "act_003",
    "title": "Ver una película completa",
    "description": "Elijan una película que ambos quieran ver. Puede ser algo nuevo o un clásico que aman.",
    "tags": ["movie", "film", "indoor", "passive", "entertainment", "relaxing"],
    "min_duration_min": 90,
    "max_duration_min": 180,
    "intensity": 0,
    "cost": 0,
    "participants": 2,
    "required_assets": ["Discord", "Snacks opcionales"],
    "suitability": {
      "mood": ["tired", "calm", "fun"],
      "time_of_day": ["evening", "night"]
    },
    "steps": [
      "Elijan película (pueden usar ruleta si no se deciden)",
      "Preparen el ambiente (luces, snacks, camita)",
      "Apaguen distracciones",
      "Disfruten sin pausas innecesarias"
    ]
  },
  {
    "id": "act_004",
    "title": "Armar un puzzle juntos",
    "description": "Trabajen en equipo para completar un rompecabezas. Es relajante y satisfactorio.",
    "tags": ["puzzle", "indoor", "calm", "cooperative", "meditative"],
    "min_duration_min": 30,
    "max_duration_min": 120,
    "intensity": 0,
    "cost": 0,
    "participants": 2,
    "required_assets": ["Puzzle"],
    "suitability": {
      "mood": ["calm", "tired"],
      "time_of_day": ["afternoon", "evening", "night"]
    },
    "steps": [
      "Elijan un puzzle (60-100 piezas recomendado)",
      "Organicen las piezas (bordes primero)",
      "Pónganse música o podcast de fondo",
      "Trabajen juntos sin prisa"
    ]
  },
  {
    "id": "act_005",
    "title": "Tener una conversación profunda",
    "description": "Apaguen todo y hablen de verdad. Usen preguntas interesantes o hablen de lo que les preocupa/emociona.",
    "tags": ["conversation", "intimate", "indoor", "passive", "connection", "emotional"],
    "min_duration_min": 20,
    "max_duration_min": 90,
    "intensity": 0,
    "cost": 0,
    "participants": 2,
    "required_assets": ["Solo ustedes"],
    "suitability": {
      "mood": ["calm", "tired"],
      "time_of_day": ["evening", "night"]
    },
    "steps": [
      "Apaguen notificaciones y distracciones",
      "Empiecen con una pregunta abierta",
      "Escuchen de verdad, sin juzgar",
      "Compartan honestamente"
    ]
  },
  {
    "id": "act_006",
    "title": "Organizar fotos o recuerdos juntos",
    "description": "Revisen fotos viejas del celular, hagan un álbum digital, o impriman algunas para guardar.",
    "tags": ["memories", "photos", "indoor", "passive", "nostalgic", "intimate"],
    "min_duration_min": 30,
    "max_duration_min": 90,
    "intensity": 0,
    "cost": 0,
    "participants": 2,
    "required_assets": ["Celularcon fotos"],
    "suitability": {
      "mood": ["calm", "fun"],
      "time_of_day": ["afternoon", "evening"]
    },
    "steps": [
      "Abran galería de fotos",
      "Elijan favoritas",
      "Comenten los recuerdos",
      "Organicen en carpetas o álbum",
      "Consideren imprimir algunas"
    ]
  }
]
